{"name":"Nueva Contraseña","id":"login;nueva-contraseña","testSteps":[{"number":1,"description":"Given que el usuario se encuentra en la pagina de automationpractice","duration":7086,"startTime":"2021-03-31T08:28:47.226377-05:00[America/Bogota]","screenshots":[{"screenshot":"a5c593a3ec2d01d44a44b5d082c924e4cbbbc7102af69355894b684c94a1a5bb.png","timeStamp":1617197327642},{"screenshot":"7b2ba2a48467aed62836bc76f6f517b02dae6709b7868ed892e601d992d2ac92.png","timeStamp":1617197334312}],"result":"SUCCESS","precondition":false,"level":0,"children":[{"number":2,"description":"Cristian ir a","duration":6665,"startTime":"2021-03-31T08:28:47.644186400-05:00[America/Bogota]","screenshots":[{"screenshot":"a5c593a3ec2d01d44a44b5d082c924e4cbbbc7102af69355894b684c94a1a5bb.png","timeStamp":1617197327647},{"screenshot":"7b2ba2a48467aed62836bc76f6f517b02dae6709b7868ed892e601d992d2ac92.png","timeStamp":1617197334309}],"result":"SUCCESS","precondition":false,"level":1,"children":[{"number":3,"description":"Cristian opens the Ui login","duration":6658,"startTime":"2021-03-31T08:28:47.649182900-05:00[America/Bogota]","screenshots":[{"screenshot":"a5c593a3ec2d01d44a44b5d082c924e4cbbbc7102af69355894b684c94a1a5bb.png","timeStamp":1617197327654},{"screenshot":"7b2ba2a48467aed62836bc76f6f517b02dae6709b7868ed892e601d992d2ac92.png","timeStamp":1617197334307}],"result":"SUCCESS","precondition":false,"level":2}]}]},{"number":4,"description":"When el usuario ingresa las credenciales fallidas","duration":7314,"startTime":"2021-03-31T08:28:54.312888300-05:00[America/Bogota]","screenshots":[{"screenshot":"09044e912b3c35a0fdc6f7f531a5861c653b9237b42df956be08d4586daa3428.png","timeStamp":1617197341627}],"result":"SUCCESS","precondition":false,"level":0,"children":[{"number":5,"description":"Cristian se loguea con datos correctos","duration":7309,"startTime":"2021-03-31T08:28:54.315888100-05:00[America/Bogota]","screenshots":[{"screenshot":"09044e912b3c35a0fdc6f7f531a5861c653b9237b42df956be08d4586daa3428.png","timeStamp":1617197341625}],"result":"SUCCESS","precondition":false,"level":1,"children":[{"number":6,"description":"Cristian clicks on #name","duration":4828,"startTime":"2021-03-31T08:28:54.320885300-05:00[America/Bogota]","screenshots":[{"screenshot":"b5d33f7691debdcb341a1d7903e2c5d230e12d9e58145016be2e220cf507e961.png","timeStamp":1617197339149}],"result":"SUCCESS","precondition":false,"level":2},{"number":7,"description":"Cristian enters \u0027lorem555@ipsum.es\u0027 into Campo de email","duration":667,"startTime":"2021-03-31T08:28:59.177853200-05:00[America/Bogota]","screenshots":[{"screenshot":"b5d33f7691debdcb341a1d7903e2c5d230e12d9e58145016be2e220cf507e961.png","timeStamp":1617197339181},{"screenshot":"cc6fb17afd16dc879aecc6389f007dd632ca127f9bdf3044d2db2558bca7fa0b.png","timeStamp":1617197339845}],"result":"SUCCESS","precondition":false,"level":2},{"number":8,"description":"Cristian enters \u0027incorrecto\u0027 into Campo de contraseña","duration":585,"startTime":"2021-03-31T08:28:59.846435-05:00[America/Bogota]","screenshots":[{"screenshot":"cc6fb17afd16dc879aecc6389f007dd632ca127f9bdf3044d2db2558bca7fa0b.png","timeStamp":1617197339849},{"screenshot":"05c6fc34d14422e6b5d36469a47dfecb9ccce184bf7e79166ca2b6003de82e04.png","timeStamp":1617197340431}],"result":"SUCCESS","precondition":false,"level":2},{"number":9,"description":"Cristian clicks on #name","duration":1189,"startTime":"2021-03-31T08:29:00.431745800-05:00[America/Bogota]","screenshots":[{"screenshot":"05c6fc34d14422e6b5d36469a47dfecb9ccce184bf7e79166ca2b6003de82e04.png","timeStamp":1617197340434},{"screenshot":"09044e912b3c35a0fdc6f7f531a5861c653b9237b42df956be08d4586daa3428.png","timeStamp":1617197341620}],"result":"SUCCESS","precondition":false,"level":2}]}]},{"number":10,"description":"And pide contraseña nueva","duration":3258,"startTime":"2021-03-31T08:29:01.628851100-05:00[America/Bogota]","screenshots":[{"screenshot":"bd0ac4ad18939656d2b4b1e8edad1856206449a6946a63f12c5d40f6e8344f74.png","timeStamp":1617197344886}],"result":"SUCCESS","precondition":false,"level":0,"children":[{"number":11,"description":"Cristian pedir nueva contraseña","duration":3253,"startTime":"2021-03-31T08:29:01.631849400-05:00[America/Bogota]","screenshots":[{"screenshot":"bd0ac4ad18939656d2b4b1e8edad1856206449a6946a63f12c5d40f6e8344f74.png","timeStamp":1617197344884}],"result":"SUCCESS","precondition":false,"level":1,"children":[{"number":12,"description":"Cristian clicks on #name","duration":1426,"startTime":"2021-03-31T08:29:01.665830700-05:00[America/Bogota]","screenshots":[{"screenshot":"0433c2629769275c631a06c8c7a1b27577ca9ef6c8c548c56964cac64968a7f8.png","timeStamp":1617197342010},{"screenshot":"ec70273edaf2f3ef7854b16864c5d3dc3fb5e440a595b57c2dd47f238e0c7a88.png","timeStamp":1617197343092}],"result":"SUCCESS","precondition":false,"level":2},{"number":13,"description":"Cristian enters \u0027lorem555@ipsum.es\u0027 into Campo de email","duration":540,"startTime":"2021-03-31T08:29:03.121004100-05:00[America/Bogota]","screenshots":[{"screenshot":"ec70273edaf2f3ef7854b16864c5d3dc3fb5e440a595b57c2dd47f238e0c7a88.png","timeStamp":1617197343125},{"screenshot":"fd4b86b014fce47f69b7e14f61711505be9a9970438bc8d57811257cac28798a.png","timeStamp":1617197343661}],"result":"SUCCESS","precondition":false,"level":2},{"number":14,"description":"Cristian clicks on #name","duration":1219,"startTime":"2021-03-31T08:29:03.662685700-05:00[America/Bogota]","screenshots":[{"screenshot":"fd4b86b014fce47f69b7e14f61711505be9a9970438bc8d57811257cac28798a.png","timeStamp":1617197343667},{"screenshot":"bd0ac4ad18939656d2b4b1e8edad1856206449a6946a63f12c5d40f6e8344f74.png","timeStamp":1617197344881}],"result":"SUCCESS","precondition":false,"level":2}]}]},{"number":15,"description":"Then se despliega un mensaje de email de recupero enviado","duration":31,"startTime":"2021-03-31T08:29:04.886986-05:00[America/Bogota]","screenshots":[{"screenshot":"bd0ac4ad18939656d2b4b1e8edad1856206449a6946a63f12c5d40f6e8344f74.png","timeStamp":1617197344918}],"result":"SUCCESS","precondition":false,"level":0}],"userStory":{"id":"login","storyName":"Login","path":"file:///C:/Users/POR00028/Desktop/CapacitacionAutomation-main/src/test/resources/features/Login.feature","narrative":"\tcomo usuario\n\tquiero loguearme en la pagina\n\tpara acceder a mi usuario","type":"feature"},"featureTag":{"name":"Features/Login","type":"feature","displayName":"Features/Login"},"title":"Nueva Contraseña","description":"","backgroundTitle":"","backgroundDescription":"","tags":[{"name":"Login","type":"feature","displayName":"Login"}],"startTime":"2021-03-31T08:28:45.555074100-05:00[America/Bogota]","duration":19363,"projectKey":"","sessionId":"33b9a9ea37fec72ac95fb20a76c6a6ea","driver":"chrome","isManualTestingUpToDate":false,"manual":false,"testSource":"Cucumber","actors":[{"name":"Cristian","can":["browse the web"]},{"name":"usuario","can":["browse the web"]}],"result":"SUCCESS"}